bayesdawn/__init__.py
bayesdawn/dasampler.py
bayesdawn/datamodel.py
bayesdawn/likelihoodmodel.py
bayesdawn/posteriormodel.py
bayesdawn/psdmodel.py
bayesdawn/psdsampler.py
bayesdawn/samplers.py
bayesdawn/algebra/__init__.py
bayesdawn/algebra/fastoeplitz.py
bayesdawn/algebra/matrixalgebra.py
bayesdawn/gaps/__init__.py
bayesdawn/gaps/gapgenerator.py
bayesdawn/gaps/leakage.py
bayesdawn/gaps/operators.py
bayesdawn/utils/__init__.py
bayesdawn/utils/loadings.py
bayesdawn/utils/physics.py
bayesdawn/utils/postprocess.py
bayesdawn/utils/preprocess.py
bayesdawn/waveforms/__init__.py
bayesdawn/waveforms/coeffs.py
bayesdawn/waveforms/lisaresp.py
bayesdawn/waveforms/wavefuncs.py
bayesdawn-0.1.0.dist-info/LICENSE
bayesdawn-0.1.0.dist-info/METADATA
bayesdawn-0.1.0.dist-info/WHEEL
bayesdawn-0.1.0.dist-info/top_level.txt
bayesdawn-0.1.0.dist-info/RECORD
