Metadata-Version: 2.1
Name: bayesdawn
Version: 0.1.0
Summary: a bayesian data augmentation algorithm
Home-page: https://github.com/qbaghi/bayesdawn
Author: Quentin Baghi
Author-email: quentin.baghi@protonmail.com
License: UNKNOWN
Keywords: bayesesian data analysis
Platform: UNKNOWN
Classifier: Development Status :: 3 - Alpha
Classifier: Intended Audience :: Developers
Classifier: Topic :: Software Development :: Build Tools
Classifier: License :: OSI Approved :: GNU General Public License (GPL)
Classifier: Programming Language :: Python :: 3
Classifier: Programming Language :: Python :: 3.4
Classifier: Programming Language :: Python :: 3.5
Classifier: Programming Language :: Python :: 3.6
Classifier: Programming Language :: Python :: 3.7
Requires-Python: >=3.5
Requires-Dist: cython
Requires-Dist: h5py
Requires-Dist: scipy
Requires-Dist: numpy
Requires-Dist: corner
Requires-Dist: pyfftw
